MANIFEST.in
README.md
setup.py
glasseye/__init__.py
glasseye/__main__.py
glasseye.egg-info/PKG-INFO
glasseye.egg-info/SOURCES.txt
glasseye.egg-info/dependency_links.txt
glasseye.egg-info/entry_points.txt
glasseye.egg-info/not-zip-safe
glasseye.egg-info/requires.txt
glasseye.egg-info/top_level.txt
glasseye/css/GlasseyeCharts.css
glasseye/css/colorbrewer.css
glasseye/css/glasseyeCharts.css
glasseye/css/tufte.css
glasseye/demo/Tufte.gif
glasseye/demo/markdownExample.md
glasseye/demo/data/activeDecidedSim.csv
glasseye/demo/data/lineplotExample.csv
glasseye/demo/data/share.csv
glasseye/js/GlasseyeCharts.js
glasseye/js/GlasseyeCharts.min.js
glasseye/js/colorbrewer.js
glasseye/js/d3.min.js
glasseye/js/d3.tip.v0.6.3.js
glasseye/js/glasseyeCharts.js
glasseye/js/glasseyeCharts.min.js
glasseye/js/glasseyePictograms.js
glasseye/js/jquery-1.11.3.min.js
glasseye/js/venn.js
glasseye/templates/pandocHTML.html
glasseye/templates/tufteTemplate.html