Metadata-Version: 1.0
Name: glasseye
Version: 0.1.17
Summary: A python module for converting markdown documents into the glasseye format
Home-page: https://github.com/coppeliaMLA/glasseye
Author: coppeliamla
Author-email: info@coppelia.io
License: MIT
Platform: UNKNOWN
